djangojsendresponses-0.1.1.dist-info/METADATA
djangojsendresponses-0.1.1.dist-info/RECORD
djangojsendresponses-0.1.1.dist-info/WHEEL
djangojsendresponses-0.1.1.dist-info/top_level.txt
jsend_responses/__init__.py
jsend_responses/responses.py
