Metadata-Version: 2.1
Name: djangojsendresponses
Version: 0.1.1
Summary: Ready Jsend specified response classes.
Home-page: https://github.com/Ibrohimbek/django-jsend-responses
Author: Ibrohim Ermatov
Author-email: ibrohimbek@gmail.com
License: UNKNOWN
Platform: UNKNOWN
Classifier: Development Status :: 2 - Pre-Alpha
Classifier: Environment :: Web Environment
Classifier: Framework :: Django
Classifier: Framework :: Django :: 1.11
Classifier: Framework :: Django :: 2.0
Classifier: Framework :: Django :: 2.1
Classifier: Intended Audience :: Developers
Classifier: Programming Language :: Python
Classifier: Programming Language :: Python :: 3
Classifier: Programming Language :: Python :: 3.6
